{
  "name": "Aalu aur Qeemay kay Kabab Recipe | Rida Aftab | Masala TV",
  "ingredients": "Ingredients for Aalu aur Qeemay kay Kabab Recipe: Mince ½ kg Cumin Seeds 2tsp Garam Masala Powder 1 tsp Salt 1tsp Ginger Garlic Paste2 tsp Potato (boiled) 2 Eggs 2 Coriander Leaves as required Finely Chopped Green Chilies as required Tomato 1 Oil (for frying) as required",
  "instructions": "In a bowl, add Mince, Boiled Potato, Cumin Seeds, Garam Masala Powder, Salt, Ginger Garlic Paste, Tomato, Coriander Leaves, Finely Chopped Green Chilies and mix well. Now make kababs and dip in egg, fry in heat oil. Delicious Aalu aur Qeemay kay Kabab is ready.",
  "prepTime": 30.0,
  "cookTime": 45,
  "totalTime": 75,
  "recipeYield": "2",
  "calories": 150,
  "youtube_link": "https://youtu.be/",
  "category": "Breakfasts"
}