{
  "name": "Highway Mutton Karahi Recipe | Masala TV",
  "ingredients": "Ingredients for Highway Mutton Karahi Recipe: Boiled mutton ½ kg Tomato ½ kg Boiled Onion Paste 1 cup Ginger Garlic 1 tbsp Whole Black Pepper 1 tsp Cinnamon 1 stick Coriander Seeds 1 tsp Fennel Seeds 1 tsp Cumin Seeds 1 tsp Carom Seeds 1 tsp Whole Red Chili 6 Red Chili Powder ½ tsp Turmeric Powder ½ tsp Salt 1 tsp Fenugreek Leaf 1 tbsp Ginger Slice 2 tbsp Fresh Coriander ½ bunch Green Chili 4 Clarified butter 1 cup",
  "instructions": "Blend all the whole spices. Meanwhile, heat clarified butter in a wok. Add onions, ginger garlic, and boiled mutton. Cook well. Then add tomatoes, turmeric powder, red chili powder and salt. Mix everything well and cover the lid. Once it is all well combined, cook on a high heat for 5 minutes. Now add the whole spice mixture, and green chilies, cook well. In the end, garnish with fresh coriander and ginger slices.",
  "prepTime": 15.0,
  "cookTime": 20,
  "totalTime": 35,
  "recipeYield": "4",
  "calories": 150,
  "youtube_link": "https://youtu.be/",
  "category": "main course"
}